memcp/__init__.py
memcp/__main__.py
memcp/database.py
memcp/mcp_server.py
memcp/tools.py
memcp/migrations/env.py
memcp/migrations/versions/001_create_memories_table.py
memcp/migrations/versions/002_create_keywords_table.py
memcp/tests/__init__.py
memcp/tests/test_database.py
memcp/tests/test_init.py
memcp/tests/test_mcp_server.py
memcp/tests/test_migrations.py
memcp/tests/test_tools.py
memcp-2025.6.28.7206.dist-info/METADATA
memcp-2025.6.28.7206.dist-info/WHEEL
memcp-2025.6.28.7206.dist-info/entry_points.txt
memcp-2025.6.28.7206.dist-info/top_level.txt
memcp-2025.6.28.7206.dist-info/RECORD
