Metadata-Version: 2.4
Name: memcp
Version: 2025.6.28.7206
Summary: Memory for Model Context Protocol
Author-email: Moshe Zadka <moshez@zadka.club>
License: Permission is hereby granted, free of charge, to any person obtaining a
Project-URL: Homepage, https://github.com/moshez/memcp
Requires-Dist: gather
Requires-Dist: commander_data
Requires-Dist: alembic
Requires-Dist: sqlalchemy
Requires-Dist: mcp
Provides-Extra: tests
Requires-Dist: virtue; extra == "tests"
Requires-Dist: pyhamcrest; extra == "tests"
Requires-Dist: coverage; extra == "tests"
Provides-Extra: mypy
Requires-Dist: mypy; extra == "mypy"
Provides-Extra: lint
Requires-Dist: flake8; extra == "lint"
Requires-Dist: black; extra == "lint"
Provides-Extra: docs
Requires-Dist: sphinx; extra == "docs"
